{
    "en": {
        "lang_label": "English",
        "feeds": {
            "latest": [
                {
                    "type": "rss",
                    "updated_at": "2021-12-10T04:12:47.978021"
                },
                {
                    "type": "atom",
                    "updated_at": "2021-12-10T04:12:47.988862"
                }
            ],
            "info": [
                {
                    "type": "rss",
                    "updated_at": "2021-12-10T04:12:48.920539"
                },
                {
                    "type": "atom",
                    "updated_at": "2021-12-10T04:12:48.931492"
                }
            ],
            "updates": [
                {
                    "type": "rss",
                    "updated_at": "2021-12-10T04:12:49.673499"
                },
                {
                    "type": "atom",
                    "updated_at": "2021-12-10T04:12:49.682136"
                }
            ],
            "events": [
                {
                    "type": "rss",
                    "updated_at": "2021-12-10T04:12:50.421754"
                },
                {
                    "type": "atom",
                    "updated_at": "2021-12-10T04:12:50.431066"
                }
            ],
            "all-articles": [
                {
                    "type": "rss",
                    "updated_at": "2021-12-10T04:12:50.461886"
                },
                {
                    "type": "atom",
                    "updated_at": "2021-12-10T04:12:50.476818"
                }
            ]
        }
    },
    "fr": {
        "lang_label": "French",
        "feeds": {
            "latest": [
                {
                    "type": "rss",
                    "updated_at": "2021-12-10T04:12:51.401627"
                },
                {
                    "type": "atom",
                    "updated_at": "2021-12-10T04:12:51.412526"
                }
            ],
            "info": [
                {
                    "type": "rss",
                    "updated_at": "2021-12-10T04:12:52.343873"
                },
                {
                    "type": "atom",
                    "updated_at": "2021-12-10T04:12:52.354906"
                }
            ],
            "updates": [
                {
                    "type": "rss",
                    "updated_at": "2021-12-10T04:12:53.094232"
                },
                {
                    "type": "atom",
                    "updated_at": "2021-12-10T04:12:53.103709"
                }
            ],
            "events": [
                {
                    "type": "rss",
                    "updated_at": "2021-12-10T04:12:53.846407"
                },
                {
                    "type": "atom",
                    "updated_at": "2021-12-10T04:12:53.855059"
                }
            ],
            "all-articles": [
                {
                    "type": "rss",
                    "updated_at": "2021-12-10T04:12:53.884144"
                },
                {
                    "type": "atom",
                    "updated_at": "2021-12-10T04:12:53.898793"
                }
            ]
        }
    },
    "zh-tw": {
        "lang_label": "Chinese",
        "feeds": {
            "latest": [
                {
                    "type": "rss",
                    "updated_at": "2021-12-10T04:12:54.828414"
                },
                {
                    "type": "atom",
                    "updated_at": "2021-12-10T04:12:54.839471"
                }
            ],
            "info": [
                {
                    "type": "rss",
                    "updated_at": "2021-12-10T04:12:55.767792"
                },
                {
                    "type": "atom",
                    "updated_at": "2021-12-10T04:12:55.778849"
                }
            ],
            "updates": [
                {
                    "type": "rss",
                    "updated_at": "2021-12-10T04:12:56.523209"
                },
                {
                    "type": "atom",
                    "updated_at": "2021-12-10T04:12:56.534748"
                }
            ],
            "events": [
                {
                    "type": "rss",
                    "updated_at": "2021-12-10T04:12:57.289156"
                },
                {
                    "type": "atom",
                    "updated_at": "2021-12-10T04:12:57.297592"
                }
            ],
            "all-articles": [
                {
                    "type": "rss",
                    "updated_at": "2021-12-10T04:12:57.329214"
                },
                {
                    "type": "atom",
                    "updated_at": "2021-12-10T04:12:57.343953"
                }
            ]
        }
    },
    "de": {
        "lang_label": "German",
        "feeds": {
            "latest": [
                {
                    "type": "rss",
                    "updated_at": "2021-12-10T04:12:58.279852"
                },
                {
                    "type": "atom",
                    "updated_at": "2021-12-10T04:12:58.291001"
                }
            ],
            "info": [
                {
                    "type": "rss",
                    "updated_at": "2021-12-10T04:12:59.222275"
                },
                {
                    "type": "atom",
                    "updated_at": "2021-12-10T04:12:59.233536"
                }
            ],
            "updates": [
                {
                    "type": "rss",
                    "updated_at": "2021-12-10T04:12:59.976354"
                },
                {
                    "type": "atom",
                    "updated_at": "2021-12-10T04:12:59.985426"
                }
            ],
            "events": [
                {
                    "type": "rss",
                    "updated_at": "2021-12-10T04:13:00.729393"
                },
                {
                    "type": "atom",
                    "updated_at": "2021-12-10T04:13:00.737899"
                }
            ],
            "all-articles": [
                {
                    "type": "rss",
                    "updated_at": "2021-12-10T04:13:00.771504"
                },
                {
                    "type": "atom",
                    "updated_at": "2021-12-10T04:13:00.786472"
                }
            ]
        }
    },
    "es": {
        "lang_label": "Spanish",
        "feeds": {
            "latest": [
                {
                    "type": "rss",
                    "updated_at": "2021-12-10T04:13:01.717744"
                },
                {
                    "type": "atom",
                    "updated_at": "2021-12-10T04:13:01.728925"
                }
            ],
            "info": [
                {
                    "type": "rss",
                    "updated_at": "2021-12-10T04:13:02.658651"
                },
                {
                    "type": "atom",
                    "updated_at": "2021-12-10T04:13:02.669759"
                }
            ],
            "updates": [
                {
                    "type": "rss",
                    "updated_at": "2021-12-10T04:13:03.410435"
                },
                {
                    "type": "atom",
                    "updated_at": "2021-12-10T04:13:03.419190"
                }
            ],
            "events": [
                {
                    "type": "rss",
                    "updated_at": "2021-12-10T04:13:04.160990"
                },
                {
                    "type": "atom",
                    "updated_at": "2021-12-10T04:13:04.169706"
                }
            ],
            "all-articles": [
                {
                    "type": "rss",
                    "updated_at": "2021-12-10T04:13:04.203088"
                },
                {
                    "type": "atom",
                    "updated_at": "2021-12-10T04:13:04.218068"
                }
            ]
        }
    },
    "id": {
        "lang_label": "Indonesian",
        "feeds": {
            "latest": [
                {
                    "type": "rss",
                    "updated_at": "2021-12-10T04:13:05.143737"
                },
                {
                    "type": "atom",
                    "updated_at": "2021-12-10T04:13:05.154685"
                }
            ],
            "info": [
                {
                    "type": "rss",
                    "updated_at": "2021-12-10T04:13:06.084396"
                },
                {
                    "type": "atom",
                    "updated_at": "2021-12-10T04:13:06.095492"
                }
            ],
            "updates": [
                {
                    "type": "rss",
                    "updated_at": "2021-12-10T04:13:06.840635"
                },
                {
                    "type": "atom",
                    "updated_at": "2021-12-10T04:13:06.849972"
                }
            ],
            "events": [
                {
                    "type": "rss",
                    "updated_at": "2021-12-10T04:13:07.593876"
                },
                {
                    "type": "atom",
                    "updated_at": "2021-12-10T04:13:07.602560"
                }
            ],
            "all-articles": [
                {
                    "type": "rss",
                    "updated_at": "2021-12-10T04:13:07.640184"
                },
                {
                    "type": "atom",
                    "updated_at": "2021-12-10T04:13:07.655038"
                }
            ]
        }
    },
    "ja": {
        "lang_label": "Japanese",
        "feeds": {
            "latest": [
                {
                    "type": "rss",
                    "updated_at": "2021-12-10T04:13:08.406020"
                },
                {
                    "type": "atom",
                    "updated_at": "2021-12-10T04:13:08.416880"
                }
            ],
            "info": [
                {
                    "type": "rss",
                    "updated_at": "2021-12-10T04:13:09.163297"
                },
                {
                    "type": "atom",
                    "updated_at": "2021-12-10T04:13:09.172122"
                }
            ],
            "updates": [
                {
                    "type": "rss",
                    "updated_at": "2021-12-10T04:13:09.928279"
                },
                {
                    "type": "atom",
                    "updated_at": "2021-12-10T04:13:09.939155"
                }
            ],
            "events": [
                {
                    "type": "rss",
                    "updated_at": "2021-12-10T04:13:10.701407"
                },
                {
                    "type": "atom",
                    "updated_at": "2021-12-10T04:13:10.712351"
                }
            ],
            "all-articles": [
                {
                    "type": "rss",
                    "updated_at": "2021-12-10T04:13:10.744838"
                },
                {
                    "type": "atom",
                    "updated_at": "2021-12-10T04:13:10.761697"
                }
            ]
        }
    },
    "ko": {
        "lang_label": "Korean",
        "feeds": {
            "latest": [
                {
                    "type": "rss",
                    "updated_at": "2021-12-10T04:13:11.686857"
                },
                {
                    "type": "atom",
                    "updated_at": "2021-12-10T04:13:11.698011"
                }
            ],
            "info": [
                {
                    "type": "rss",
                    "updated_at": "2021-12-10T04:13:12.627133"
                },
                {
                    "type": "atom",
                    "updated_at": "2021-12-10T04:13:12.638186"
                }
            ],
            "updates": [
                {
                    "type": "rss",
                    "updated_at": "2021-12-10T04:13:13.379941"
                },
                {
                    "type": "atom",
                    "updated_at": "2021-12-10T04:13:13.389087"
                }
            ],
            "events": [
                {
                    "type": "rss",
                    "updated_at": "2021-12-10T04:13:14.128527"
                },
                {
                    "type": "atom",
                    "updated_at": "2021-12-10T04:13:14.137616"
                }
            ],
            "all-articles": [
                {
                    "type": "rss",
                    "updated_at": "2021-12-10T04:13:14.169647"
                },
                {
                    "type": "atom",
                    "updated_at": "2021-12-10T04:13:14.184928"
                }
            ]
        }
    },
    "pt": {
        "lang_label": "Portuguese",
        "feeds": {
            "latest": [
                {
                    "type": "rss",
                    "updated_at": "2021-12-10T04:13:15.115694"
                },
                {
                    "type": "atom",
                    "updated_at": "2021-12-10T04:13:15.126930"
                }
            ],
            "info": [
                {
                    "type": "rss",
                    "updated_at": "2021-12-10T04:13:16.098704"
                },
                {
                    "type": "atom",
                    "updated_at": "2021-12-10T04:13:16.109896"
                }
            ],
            "updates": [
                {
                    "type": "rss",
                    "updated_at": "2021-12-10T04:13:16.852441"
                },
                {
                    "type": "atom",
                    "updated_at": "2021-12-10T04:13:16.861824"
                }
            ],
            "events": [
                {
                    "type": "rss",
                    "updated_at": "2021-12-10T04:13:17.601363"
                },
                {
                    "type": "atom",
                    "updated_at": "2021-12-10T04:13:17.610692"
                }
            ],
            "all-articles": [
                {
                    "type": "rss",
                    "updated_at": "2021-12-10T04:13:17.645467"
                },
                {
                    "type": "atom",
                    "updated_at": "2021-12-10T04:13:17.660601"
                }
            ]
        }
    },
    "ru": {
        "lang_label": "Russian",
        "feeds": {
            "latest": [
                {
                    "type": "rss",
                    "updated_at": "2021-12-10T04:13:18.590455"
                },
                {
                    "type": "atom",
                    "updated_at": "2021-12-10T04:13:18.601834"
                }
            ],
            "info": [
                {
                    "type": "rss",
                    "updated_at": "2021-12-10T04:13:19.534350"
                },
                {
                    "type": "atom",
                    "updated_at": "2021-12-10T04:13:19.545761"
                }
            ],
            "updates": [
                {
                    "type": "rss",
                    "updated_at": "2021-12-10T04:13:20.283766"
                },
                {
                    "type": "atom",
                    "updated_at": "2021-12-10T04:13:20.292524"
                }
            ],
            "events": [
                {
                    "type": "rss",
                    "updated_at": "2021-12-10T04:13:21.034576"
                },
                {
                    "type": "atom",
                    "updated_at": "2021-12-10T04:13:21.044075"
                }
            ],
            "all-articles": [
                {
                    "type": "rss",
                    "updated_at": "2021-12-10T04:13:21.077207"
                },
                {
                    "type": "atom",
                    "updated_at": "2021-12-10T04:13:21.093065"
                }
            ]
        }
    },
    "th": {
        "lang_label": "Thai",
        "feeds": {
            "latest": [
                {
                    "type": "rss",
                    "updated_at": "2021-12-10T04:13:22.023943"
                },
                {
                    "type": "atom",
                    "updated_at": "2021-12-10T04:13:22.034911"
                }
            ],
            "info": [
                {
                    "type": "rss",
                    "updated_at": "2021-12-10T04:13:22.962589"
                },
                {
                    "type": "atom",
                    "updated_at": "2021-12-10T04:13:22.973645"
                }
            ],
            "updates": [
                {
                    "type": "rss",
                    "updated_at": "2021-12-10T04:13:23.717771"
                },
                {
                    "type": "atom",
                    "updated_at": "2021-12-10T04:13:23.726970"
                }
            ],
            "events": [
                {
                    "type": "rss",
                    "updated_at": "2021-12-10T04:13:24.470264"
                },
                {
                    "type": "atom",
                    "updated_at": "2021-12-10T04:13:24.478938"
                }
            ],
            "all-articles": [
                {
                    "type": "rss",
                    "updated_at": "2021-12-10T04:13:24.510065"
                },
                {
                    "type": "atom",
                    "updated_at": "2021-12-10T04:13:24.525539"
                }
            ]
        }
    },
    "vi": {
        "lang_label": "Vietnamese",
        "feeds": {
            "latest": [
                {
                    "type": "rss",
                    "updated_at": "2021-12-10T04:13:25.276100"
                },
                {
                    "type": "atom",
                    "updated_at": "2021-12-10T04:13:25.286978"
                }
            ],
            "info": [
                {
                    "type": "rss",
                    "updated_at": "2021-12-10T04:13:26.039227"
                },
                {
                    "type": "atom",
                    "updated_at": "2021-12-10T04:13:26.050094"
                }
            ],
            "updates": [
                {
                    "type": "rss",
                    "updated_at": "2021-12-10T04:13:26.786850"
                },
                {
                    "type": "atom",
                    "updated_at": "2021-12-10T04:13:26.796308"
                }
            ],
            "events": [
                {
                    "type": "rss",
                    "updated_at": "2021-12-10T04:13:27.534468"
                },
                {
                    "type": "atom",
                    "updated_at": "2021-12-10T04:13:27.543138"
                }
            ],
            "all-articles": [
                {
                    "type": "rss",
                    "updated_at": "2021-12-10T04:13:27.574804"
                },
                {
                    "type": "atom",
                    "updated_at": "2021-12-10T04:13:27.589327"
                }
            ]
        }
    }
}