{
    "en": {
        "lang_label": "English",
        "feeds": {
            "latest": [
                {
                    "type": "rss",
                    "updated_at": "2021-09-02T09:08:43.890642"
                },
                {
                    "type": "atom",
                    "updated_at": "2021-09-02T09:08:43.903142"
                }
            ],
            "info": [
                {
                    "type": "rss",
                    "updated_at": "2021-09-02T09:08:44.180919"
                },
                {
                    "type": "atom",
                    "updated_at": "2021-09-02T09:08:44.193768"
                }
            ],
            "updates": [
                {
                    "type": "rss",
                    "updated_at": "2021-09-02T09:08:44.229017"
                },
                {
                    "type": "atom",
                    "updated_at": "2021-09-02T09:08:44.238755"
                }
            ],
            "events": [
                {
                    "type": "rss",
                    "updated_at": "2021-09-02T09:08:44.289085"
                },
                {
                    "type": "atom",
                    "updated_at": "2021-09-02T09:08:44.299161"
                }
            ],
            "all-articles": [
                {
                    "type": "rss",
                    "updated_at": "2021-09-02T09:08:44.333216"
                },
                {
                    "type": "atom",
                    "updated_at": "2021-09-02T09:08:44.350769"
                }
            ]
        }
    },
    "fr": {
        "lang_label": "French",
        "feeds": {
            "latest": [
                {
                    "type": "rss",
                    "updated_at": "2021-09-02T09:08:44.631857"
                },
                {
                    "type": "atom",
                    "updated_at": "2021-09-02T09:08:44.644592"
                }
            ],
            "info": [
                {
                    "type": "rss",
                    "updated_at": "2021-09-02T09:08:44.918667"
                },
                {
                    "type": "atom",
                    "updated_at": "2021-09-02T09:08:44.930574"
                }
            ],
            "updates": [
                {
                    "type": "rss",
                    "updated_at": "2021-09-02T09:08:45.186480"
                },
                {
                    "type": "atom",
                    "updated_at": "2021-09-02T09:08:45.196761"
                }
            ],
            "events": [
                {
                    "type": "rss",
                    "updated_at": "2021-09-02T09:08:45.598178"
                },
                {
                    "type": "atom",
                    "updated_at": "2021-09-02T09:08:45.608652"
                }
            ],
            "all-articles": [
                {
                    "type": "rss",
                    "updated_at": "2021-09-02T09:08:45.641835"
                },
                {
                    "type": "atom",
                    "updated_at": "2021-09-02T09:08:45.658909"
                }
            ]
        }
    },
    "zh-tw": {
        "lang_label": "Chinese",
        "feeds": {
            "latest": [
                {
                    "type": "rss",
                    "updated_at": "2021-09-02T09:08:45.710009"
                },
                {
                    "type": "atom",
                    "updated_at": "2021-09-02T09:08:45.721657"
                }
            ],
            "info": [
                {
                    "type": "rss",
                    "updated_at": "2021-09-02T09:08:45.999884"
                },
                {
                    "type": "atom",
                    "updated_at": "2021-09-02T09:08:46.011889"
                }
            ],
            "updates": [
                {
                    "type": "rss",
                    "updated_at": "2021-09-02T09:08:46.427495"
                },
                {
                    "type": "atom",
                    "updated_at": "2021-09-02T09:08:46.436863"
                }
            ],
            "events": [
                {
                    "type": "rss",
                    "updated_at": "2021-09-02T09:08:46.468452"
                },
                {
                    "type": "atom",
                    "updated_at": "2021-09-02T09:08:46.477360"
                }
            ],
            "all-articles": [
                {
                    "type": "rss",
                    "updated_at": "2021-09-02T09:08:46.507877"
                },
                {
                    "type": "atom",
                    "updated_at": "2021-09-02T09:08:46.522964"
                }
            ]
        }
    },
    "de": {
        "lang_label": "German",
        "feeds": {
            "latest": [
                {
                    "type": "rss",
                    "updated_at": "2021-09-02T09:08:46.948282"
                },
                {
                    "type": "atom",
                    "updated_at": "2021-09-02T09:08:46.959509"
                }
            ],
            "info": [
                {
                    "type": "rss",
                    "updated_at": "2021-09-02T09:08:47.232633"
                },
                {
                    "type": "atom",
                    "updated_at": "2021-09-02T09:08:47.245532"
                }
            ],
            "updates": [
                {
                    "type": "rss",
                    "updated_at": "2021-09-02T09:08:47.309695"
                },
                {
                    "type": "atom",
                    "updated_at": "2021-09-02T09:08:47.319438"
                }
            ],
            "events": [
                {
                    "type": "rss",
                    "updated_at": "2021-09-02T09:08:47.353585"
                },
                {
                    "type": "atom",
                    "updated_at": "2021-09-02T09:08:47.362724"
                }
            ],
            "all-articles": [
                {
                    "type": "rss",
                    "updated_at": "2021-09-02T09:08:47.393992"
                },
                {
                    "type": "atom",
                    "updated_at": "2021-09-02T09:08:47.410048"
                }
            ]
        }
    },
    "es": {
        "lang_label": "Spanish",
        "feeds": {
            "latest": [
                {
                    "type": "rss",
                    "updated_at": "2021-09-02T09:08:47.461503"
                },
                {
                    "type": "atom",
                    "updated_at": "2021-09-02T09:08:47.473656"
                }
            ],
            "info": [
                {
                    "type": "rss",
                    "updated_at": "2021-09-02T09:08:47.549738"
                },
                {
                    "type": "atom",
                    "updated_at": "2021-09-02T09:08:47.560616"
                }
            ],
            "updates": [
                {
                    "type": "rss",
                    "updated_at": "2021-09-02T09:08:47.602461"
                },
                {
                    "type": "atom",
                    "updated_at": "2021-09-02T09:08:47.610999"
                }
            ],
            "events": [
                {
                    "type": "rss",
                    "updated_at": "2021-09-02T09:08:47.658344"
                },
                {
                    "type": "atom",
                    "updated_at": "2021-09-02T09:08:47.668722"
                }
            ],
            "all-articles": [
                {
                    "type": "rss",
                    "updated_at": "2021-09-02T09:08:47.698387"
                },
                {
                    "type": "atom",
                    "updated_at": "2021-09-02T09:08:47.713289"
                }
            ]
        }
    },
    "id": {
        "lang_label": "Indonesian",
        "feeds": {
            "latest": [
                {
                    "type": "rss",
                    "updated_at": "2021-09-02T09:08:47.761582"
                },
                {
                    "type": "atom",
                    "updated_at": "2021-09-02T09:08:47.772397"
                }
            ],
            "info": [
                {
                    "type": "rss",
                    "updated_at": "2021-09-02T09:08:47.819341"
                },
                {
                    "type": "atom",
                    "updated_at": "2021-09-02T09:08:47.830976"
                }
            ],
            "updates": [
                {
                    "type": "rss",
                    "updated_at": "2021-09-02T09:08:47.873185"
                },
                {
                    "type": "atom",
                    "updated_at": "2021-09-02T09:08:47.883625"
                }
            ],
            "events": [
                {
                    "type": "rss",
                    "updated_at": "2021-09-02T09:08:47.915986"
                },
                {
                    "type": "atom",
                    "updated_at": "2021-09-02T09:08:47.924278"
                }
            ],
            "all-articles": [
                {
                    "type": "rss",
                    "updated_at": "2021-09-02T09:08:47.952288"
                },
                {
                    "type": "atom",
                    "updated_at": "2021-09-02T09:08:47.966584"
                }
            ]
        }
    },
    "ja": {
        "lang_label": "Japanese",
        "feeds": {
            "latest": [
                {
                    "type": "rss",
                    "updated_at": "2021-09-02T09:08:48.012981"
                },
                {
                    "type": "atom",
                    "updated_at": "2021-09-02T09:08:48.056464"
                }
            ],
            "info": [
                {
                    "type": "rss",
                    "updated_at": "2021-09-02T09:08:48.091072"
                },
                {
                    "type": "atom",
                    "updated_at": "2021-09-02T09:08:48.100519"
                }
            ],
            "updates": [
                {
                    "type": "rss",
                    "updated_at": "2021-09-02T09:08:48.148069"
                },
                {
                    "type": "atom",
                    "updated_at": "2021-09-02T09:08:48.158891"
                }
            ],
            "events": [
                {
                    "type": "rss",
                    "updated_at": "2021-09-02T09:08:48.479630"
                },
                {
                    "type": "atom",
                    "updated_at": "2021-09-02T09:08:48.491493"
                }
            ],
            "all-articles": [
                {
                    "type": "rss",
                    "updated_at": "2021-09-02T09:08:48.527349"
                },
                {
                    "type": "atom",
                    "updated_at": "2021-09-02T09:08:48.545830"
                }
            ]
        }
    },
    "ko": {
        "lang_label": "Korean",
        "feeds": {
            "latest": [
                {
                    "type": "rss",
                    "updated_at": "2021-09-02T09:08:48.600750"
                },
                {
                    "type": "atom",
                    "updated_at": "2021-09-02T09:08:48.618315"
                }
            ],
            "info": [
                {
                    "type": "rss",
                    "updated_at": "2021-09-02T09:08:48.669089"
                },
                {
                    "type": "atom",
                    "updated_at": "2021-09-02T09:08:48.682700"
                }
            ],
            "updates": [
                {
                    "type": "rss",
                    "updated_at": "2021-09-02T09:08:48.722513"
                },
                {
                    "type": "atom",
                    "updated_at": "2021-09-02T09:08:48.731794"
                }
            ],
            "events": [
                {
                    "type": "rss",
                    "updated_at": "2021-09-02T09:08:48.765626"
                },
                {
                    "type": "atom",
                    "updated_at": "2021-09-02T09:08:48.774031"
                }
            ],
            "all-articles": [
                {
                    "type": "rss",
                    "updated_at": "2021-09-02T09:08:48.807948"
                },
                {
                    "type": "atom",
                    "updated_at": "2021-09-02T09:08:48.824966"
                }
            ]
        }
    },
    "pt": {
        "lang_label": "Portuguese",
        "feeds": {
            "latest": [
                {
                    "type": "rss",
                    "updated_at": "2021-09-02T09:08:48.876821"
                },
                {
                    "type": "atom",
                    "updated_at": "2021-09-02T09:08:48.888992"
                }
            ],
            "info": [
                {
                    "type": "rss",
                    "updated_at": "2021-09-02T09:08:48.939030"
                },
                {
                    "type": "atom",
                    "updated_at": "2021-09-02T09:08:48.949740"
                }
            ],
            "updates": [
                {
                    "type": "rss",
                    "updated_at": "2021-09-02T09:08:48.984857"
                },
                {
                    "type": "atom",
                    "updated_at": "2021-09-02T09:08:48.997212"
                }
            ],
            "events": [
                {
                    "type": "rss",
                    "updated_at": "2021-09-02T09:08:49.033080"
                },
                {
                    "type": "atom",
                    "updated_at": "2021-09-02T09:08:49.041494"
                }
            ],
            "all-articles": [
                {
                    "type": "rss",
                    "updated_at": "2021-09-02T09:08:49.073129"
                },
                {
                    "type": "atom",
                    "updated_at": "2021-09-02T09:08:49.088567"
                }
            ]
        }
    },
    "ru": {
        "lang_label": "Russian",
        "feeds": {
            "latest": [
                {
                    "type": "rss",
                    "updated_at": "2021-09-02T09:08:49.148169"
                },
                {
                    "type": "atom",
                    "updated_at": "2021-09-02T09:08:49.159635"
                }
            ],
            "info": [
                {
                    "type": "rss",
                    "updated_at": "2021-09-02T09:08:49.212885"
                },
                {
                    "type": "atom",
                    "updated_at": "2021-09-02T09:08:49.225603"
                }
            ],
            "updates": [
                {
                    "type": "rss",
                    "updated_at": "2021-09-02T09:08:49.260353"
                },
                {
                    "type": "atom",
                    "updated_at": "2021-09-02T09:08:49.270043"
                }
            ],
            "events": [
                {
                    "type": "rss",
                    "updated_at": "2021-09-02T09:08:49.303208"
                },
                {
                    "type": "atom",
                    "updated_at": "2021-09-02T09:08:49.311607"
                }
            ],
            "all-articles": [
                {
                    "type": "rss",
                    "updated_at": "2021-09-02T09:08:49.346481"
                },
                {
                    "type": "atom",
                    "updated_at": "2021-09-02T09:08:49.362846"
                }
            ]
        }
    },
    "th": {
        "lang_label": "Thai",
        "feeds": {
            "latest": [
                {
                    "type": "rss",
                    "updated_at": "2021-09-02T09:08:49.413811"
                },
                {
                    "type": "atom",
                    "updated_at": "2021-09-02T09:08:49.425186"
                }
            ],
            "info": [
                {
                    "type": "rss",
                    "updated_at": "2021-09-02T09:08:49.482113"
                },
                {
                    "type": "atom",
                    "updated_at": "2021-09-02T09:08:49.494628"
                }
            ],
            "updates": [
                {
                    "type": "rss",
                    "updated_at": "2021-09-02T09:08:49.528150"
                },
                {
                    "type": "atom",
                    "updated_at": "2021-09-02T09:08:49.538565"
                }
            ],
            "events": [
                {
                    "type": "rss",
                    "updated_at": "2021-09-02T09:08:49.579808"
                },
                {
                    "type": "atom",
                    "updated_at": "2021-09-02T09:08:49.588787"
                }
            ],
            "all-articles": [
                {
                    "type": "rss",
                    "updated_at": "2021-09-02T09:08:49.622739"
                },
                {
                    "type": "atom",
                    "updated_at": "2021-09-02T09:08:49.639723"
                }
            ]
        }
    },
    "vi": {
        "lang_label": "Vietnamese",
        "feeds": {
            "latest": [
                {
                    "type": "rss",
                    "updated_at": "2021-09-02T09:08:49.693043"
                },
                {
                    "type": "atom",
                    "updated_at": "2021-09-02T09:08:49.705832"
                }
            ],
            "info": [
                {
                    "type": "rss",
                    "updated_at": "2021-09-02T09:08:49.759395"
                },
                {
                    "type": "atom",
                    "updated_at": "2021-09-02T09:08:49.770787"
                }
            ],
            "updates": [
                {
                    "type": "rss",
                    "updated_at": "2021-09-02T09:08:49.810718"
                },
                {
                    "type": "atom",
                    "updated_at": "2021-09-02T09:08:49.819527"
                }
            ],
            "events": [
                {
                    "type": "rss",
                    "updated_at": "2021-09-02T09:08:49.854600"
                },
                {
                    "type": "atom",
                    "updated_at": "2021-09-02T09:08:49.864435"
                }
            ],
            "all-articles": [
                {
                    "type": "rss",
                    "updated_at": "2021-09-02T09:08:49.898900"
                },
                {
                    "type": "atom",
                    "updated_at": "2021-09-02T09:08:49.915177"
                }
            ]
        }
    }
}